[{"id":"d0f5ca67.9191e8","type":"msg-resend","z":"42b7b639.325dd8","interval":"1","intervalUnit":"secs","maximum":"4","bytopic":false,"clone":true,"firstDelayed":false,"addCounters":false,"waitForResend":false,"highRate":false,"outputCountField":"","outputMaxField":"","name":"","x":2370,"y":220,"wires":[["b18a381c.2e5bf8"]]},{"id":"6c905f49.c7653","type":"inject","z":"42b7b639.325dd8","name":"someValue","props":[{"p":"payload"}],"repeat":"","crontab":"","once":false,"onceDelay":0.1,"topic":"","payload":"someValue","payloadType":"str","x":2100,"y":220,"wires":[["d0f5ca67.9191e8"]]},{"id":"b18a381c.2e5bf8","type":"debug","z":"42b7b639.325dd8","name":"Output","active":true,"tosidebar":true,"console":false,"tostatus":false,"complete":"payload","targetType":"msg","statusVal":"","statusType":"auto","x":2530,"y":220,"wires":[]},{"id":"267d86d3.2e31ca","type":"inject","z":"42b7b639.325dd8","name":"Resend last message","props":[{"p":"resend_last_msg","v":"true","vt":"bool"}],"repeat":"","crontab":"","once":false,"onceDelay":0.1,"topic":"","x":2140,"y":320,"wires":[["d0f5ca67.9191e8"]]},{"id":"8d5a0592.2802e8","type":"inject","z":"42b7b639.325dd8","name":"anotherValue","props":[{"p":"payload"}],"repeat":"","crontab":"","once":false,"onceDelay":0.1,"topic":"","payload":"anotherValue","payloadType":"str","x":2110,"y":260,"wires":[["d0f5ca67.9191e8"]]}]
